<?xml version="1.0"?>
<Race xmlns:xsi="http://www.w3.org/2001/XMLSchema-instance" xmlns:xsd="http://www.w3.org/2001/XMLSchema">
  <Name>Air Elemental</Name>
  <ColorName>&amp;+CAir &amp;+cElemental&amp;n</ColorName>
  <DecayedName>no bones</DecayedName>
  <Key>EA</Key>
  <NumKickMessages>0</NumKickMessages>
  <InnateAbilities>
    <int>68</int>
    <int>0</int>
  </InnateAbilities>
  <Size>large</Size>
  <ClassesAvailable>none</ClassesAvailable>
  <Height>72</Height>
  <Weight>150</Weight>
  <BaseAlignment>0</BaseAlignment>
  <NaturalAC>20</NaturalAC>
  <StrModifier>130</StrModifier>
  <IntModifier>70</IntModifier>
  <WisModifier>100</WisModifier>
  <DexModifier>80</DexModifier>
  <ConModifier>130</ConModifier>
  <AgiModifier>80</AgiModifier>
  <ChaModifier>10</ChaModifier>
  <PowModifier>10</PowModifier>
  <LukModifier>100</LukModifier>
  <HpGain>0</HpGain>
  <ManaGain>0</ManaGain>
  <MoveGain>0</MoveGain>
  <ThirstModifier>-1</ThirstModifier>
  <HungerModifier>-1</HungerModifier>
  <DamageMessage>thrash</DamageMessage>
  <WalkMessage>blows</WalkMessage>
  <Filename>..\races\AirElemental.race</Filename>
  <BodyParts>skull arms legs heart brains guts hands feet fingers ears eyes</BodyParts>
  <Resistant>none</Resistant>
  <Immune>none</Immune>
  <Susceptible>none</Susceptible>
  <Vulnerable>none</Vulnerable>
  <Language>magical</Language>
  <RacewarSide>neutral</RacewarSide>
  <BaseAge>18</BaseAge>
  <MaxAge>80</MaxAge>
  <MagicResistance>0</MagicResistance>
  <Coins>false</Coins>
  <ExperienceModifier>1</ExperienceModifier>
  <Number>52</Number>
  <SaveModifiers>
    <int>0</int>
    <int>0</int>
    <int>0</int>
    <int>0</int>
    <int>0</int>
    <int>0</int>
  </SaveModifiers>
  <RaceFaction>
    <double>0</double>
    <double>0</double>
    <double>0</double>
    <double>0</double>
    <double>0</double>
    <double>0</double>
    <double>0</double>
    <double>0</double>
    <double>0</double>
    <double>0</double>
    <double>0</double>
    <double>0</double>
    <double>0</double>
    <double>0</double>
    <double>0</double>
    <double>0</double>
    <double>0</double>
    <double>0</double>
    <double>0</double>
    <double>0</double>
    <double>0</double>
    <double>0</double>
    <double>0</double>
    <double>0</double>
    <double>0</double>
    <double>0</double>
    <double>0</double>
    <double>0</double>
    <double>0</double>
    <double>0</double>
    <double>0</double>
    <double>0</double>
    <double>0</double>
    <double>0</double>
    <double>0</double>
    <double>0</double>
    <double>0</double>
    <double>0</double>
    <double>0</double>
    <double>0</double>
    <double>0</double>
    <double>0</double>
    <double>0</double>
    <double>0</double>
    <double>0</double>
    <double>0</double>
    <double>0</double>
    <double>0</double>
    <double>0</double>
    <double>0</double>
    <double>0</double>
    <double>0</double>
    <double>0</double>
    <double>0</double>
    <double>0</double>
    <double>0</double>
    <double>0</double>
    <double>0</double>
    <double>0</double>
    <double>0</double>
    <double>0</double>
    <double>0</double>
    <double>0</double>
    <double>0</double>
    <double>0</double>
    <double>0</double>
    <double>0</double>
    <double>0</double>
    <double>0</double>
    <double>0</double>
    <double>0</double>
    <double>0</double>
    <double>0</double>
    <double>0</double>
    <double>0</double>
    <double>0</double>
    <double>0</double>
    <double>0</double>
    <double>0</double>
    <double>0</double>
    <double>0</double>
    <double>0</double>
  </RaceFaction>
</Race>