<?xml version="1.0"?>
<?xml-stylesheet type="text/xsl" href="_transform.xsl"?>
<Race xmlns:xsi="http://www.w3.org/2001/XMLSchema-instance" xmlns:xsd="http://www.w3.org/2001/XMLSchema">
  <Name>Githzerai</Name>
  <ColorName>&amp;+GGith&amp;n&amp;+yzerai&amp;n</ColorName>
  <DecayedName>humanoid</DecayedName>
  <Key>GZ</Key>
  <NumKickMessages>0</NumKickMessages>
  <InnateAbilities>
    <int>331841</int>
    <int>0</int>
  </InnateAbilities>
  <Size>medium</Size>
  <ClassesAvailable>none</ClassesAvailable>
  <Height>70</Height>
  <Weight>140</Weight>
  <BaseAlignment>-975</BaseAlignment>
  <NaturalAC>100</NaturalAC>
  <StrModifier>95</StrModifier>
  <IntModifier>100</IntModifier>
  <WisModifier>100</WisModifier>
  <DexModifier>100</DexModifier>
  <ConModifier>90</ConModifier>
  <AgiModifier>100</AgiModifier>
  <ChaModifier>85</ChaModifier>
  <PowModifier>120</PowModifier>
  <LukModifier>93</LukModifier>
  <HpGain>1</HpGain>
  <ManaGain>3</ManaGain>
  <MoveGain>3</MoveGain>
  <ThirstModifier>-1</ThirstModifier>
  <HungerModifier>-1</HungerModifier>
  <DamageMessage>punch</DamageMessage>
  <WalkMessage>walks</WalkMessage>
  <Hate>Illithid githyanki</Hate>
  <Filename>..\races\Githzerai.race</Filename>
  <BodyParts>skull arms legs heart brains guts hands feet fingers ears eyes scalp</BodyParts>
  <Resistant>mental</Resistant>
  <Immune>none</Immune>
  <Susceptible>iron</Susceptible>
  <Vulnerable>none</Vulnerable>
  <Language>githzerai</Language>
  <RacewarSide>good</RacewarSide>
  <BaseAge>18</BaseAge>
  <MaxAge>80</MaxAge>
  <MagicResistance>10</MagicResistance>
  <Coins>true</Coins>
  <ExperienceModifier>2</ExperienceModifier>
  <Number>18</Number>
  <SaveModifiers>
    <int>0</int>
    <int>0</int>
    <int>0</int>
    <int>0</int>
    <int>0</int>
    <int>0</int>
  </SaveModifiers>
  <RaceFaction>
    <double>7500</double>
    <double>7500</double>
    <double>7500</double>
    <double>-7500</double>
    <double>7500</double>
    <double>-7500</double>
    <double>-7500</double>
    <double>7500</double>
    <double>-7500</double>
    <double>7500</double>
    <double>-7500</double>
    <double>-7500</double>
    <double>-7500</double>
    <double>7500</double>
    <double>7500</double>
    <double>-7500</double>
    <double>-7500</double>
    <double>-7500</double>
    <double>7500</double>
    <double>7500</double>
    <double>0</double>
    <double>-7500</double>
    <double>0</double>
    <double>-7500</double>
    <double>0</double>
    <double>0</double>
    <double>0</double>
    <double>-7500</double>
    <double>0</double>
    <double>-7500</double>
    <double>0</double>
    <double>0</double>
    <double>0</double>
    <double>0</double>
    <double>0</double>
    <double>0</double>
    <double>0</double>
    <double>0</double>
    <double>0</double>
    <double>0</double>
    <double>0</double>
    <double>0</double>
    <double>0</double>
    <double>0</double>
    <double>0</double>
    <double>0</double>
    <double>0</double>
    <double>0</double>
    <double>0</double>
    <double>0</double>
    <double>0</double>
    <double>0</double>
    <double>0</double>
    <double>0</double>
    <double>0</double>
    <double>0</double>
    <double>0</double>
    <double>0</double>
    <double>0</double>
    <double>0</double>
    <double>0</double>
    <double>0</double>
    <double>0</double>
    <double>0</double>
    <double>0</double>
    <double>0</double>
    <double>0</double>
    <double>0</double>
    <double>0</double>
    <double>0</double>
    <double>0</double>
    <double>0</double>
    <double>0</double>
    <double>0</double>
    <double>0</double>
    <double>0</double>
    <double>0</double>
    <double>0</double>
    <double>0</double>
    <double>0</double>
    <double>0</double>
    <double>0</double>
  </RaceFaction>
</Race>