<?xml version="1.0"?>
<?xml-stylesheet type="text/xsl" href="_transform.xsl"?>
<Race xmlns:xsi="http://www.w3.org/2001/XMLSchema-instance" xmlns:xsd="http://www.w3.org/2001/XMLSchema">
  <Name>Rakshasa</Name>
  <ColorName>&amp;N&amp;+LRak&amp;+Wshasa&amp;n</ColorName>
  <DecayedName>no bones</DecayedName>
  <Key>RA</Key>
  <NumKickMessages>0</NumKickMessages>
  <InnateAbilities>
    <int>1380353</int>
    <int>0</int>
  </InnateAbilities>
  <Size>medium</Size>
  <ClassesAvailable>warrior sorcerer thief assassin antipaladin elementAir elementFire elementWater hunter illusionist enchanter</ClassesAvailable>
  <Height>72</Height>
  <Weight>150</Weight>
  <BaseAlignment>-700</BaseAlignment>
  <NaturalAC>100</NaturalAC>
  <StrModifier>95</StrModifier>
  <IntModifier>105</IntModifier>
  <WisModifier>110</WisModifier>
  <DexModifier>95</DexModifier>
  <ConModifier>85</ConModifier>
  <AgiModifier>90</AgiModifier>
  <ChaModifier>90</ChaModifier>
  <PowModifier>105</PowModifier>
  <LukModifier>95</LukModifier>
  <HpGain>1</HpGain>
  <ManaGain>4</ManaGain>
  <MoveGain>3</MoveGain>
  <ThirstModifier>0</ThirstModifier>
  <HungerModifier>0</HungerModifier>
  <DamageMessage>claw</DamageMessage>
  <WalkMessage>pads</WalkMessage>
  <Filename>..\races\Rakshasa.race</Filename>
  <BodyParts>skull arms legs heart brains guts hands feet fingers ears eyes scalp</BodyParts>
  <Resistant>charm</Resistant>
  <Immune>none</Immune>
  <Susceptible>iron</Susceptible>
  <Vulnerable>none</Vulnerable>
  <Language>rakshasa</Language>
  <RacewarSide>evil</RacewarSide>
  <BaseAge>40</BaseAge>
  <MaxAge>900</MaxAge>
  <MagicResistance>25</MagicResistance>
  <Coins>true</Coins>
  <ExperienceModifier>3</ExperienceModifier>
  <Number>3</Number>
  <SaveModifiers>
    <int>0</int>
    <int>0</int>
    <int>0</int>
    <int>0</int>
    <int>0</int>
    <int>0</int>
  </SaveModifiers>
  <RaceFaction>
    <double>-7500</double>
    <double>-7500</double>
    <double>-7500</double>
    <double>7500</double>
    <double>-7500</double>
    <double>7500</double>
    <double>7500</double>
    <double>-7500</double>
    <double>7500</double>
    <double>-7500</double>
    <double>7500</double>
    <double>7500</double>
    <double>7500</double>
    <double>-7500</double>
    <double>-7500</double>
    <double>7500</double>
    <double>7500</double>
    <double>7500</double>
    <double>-7500</double>
    <double>-7500</double>
    <double>0</double>
    <double>7500</double>
    <double>0</double>
    <double>-7500</double>
    <double>0</double>
    <double>0</double>
    <double>0</double>
    <double>-7500</double>
    <double>0</double>
    <double>-7500</double>
    <double>0</double>
    <double>0</double>
    <double>0</double>
    <double>0</double>
    <double>0</double>
    <double>0</double>
    <double>0</double>
    <double>0</double>
    <double>0</double>
    <double>0</double>
    <double>0</double>
    <double>0</double>
    <double>0</double>
    <double>0</double>
    <double>0</double>
    <double>0</double>
    <double>0</double>
    <double>0</double>
    <double>0</double>
    <double>0</double>
    <double>0</double>
    <double>0</double>
    <double>0</double>
    <double>0</double>
    <double>0</double>
    <double>0</double>
    <double>0</double>
    <double>0</double>
    <double>0</double>
    <double>0</double>
    <double>0</double>
    <double>0</double>
    <double>0</double>
    <double>0</double>
    <double>0</double>
    <double>0</double>
    <double>0</double>
    <double>0</double>
    <double>0</double>
    <double>0</double>
    <double>0</double>
    <double>0</double>
    <double>0</double>
    <double>0</double>
    <double>0</double>
    <double>0</double>
    <double>0</double>
    <double>0</double>
    <double>0</double>
    <double>0</double>
    <double>0</double>
    <double>0</double>
  </RaceFaction>
</Race>